LICENSE
MANIFEST.in
README
setup.py
bflb_mcu_tool/__init__.py
bflb_mcu_tool/__main__.py
bflb_mcu_tool/config.py
bflb_mcu_tool/chips/bl602/conf/ota.toml
bflb_mcu_tool/chips/bl602/device_tree/bl_factory_params_IoTKitA_24M.dts
bflb_mcu_tool/chips/bl602/device_tree/bl_factory_params_IoTKitA_26M.dts
bflb_mcu_tool/chips/bl602/device_tree/bl_factory_params_IoTKitA_32M.dts
bflb_mcu_tool/chips/bl602/device_tree/bl_factory_params_IoTKitA_38.4M.dts
bflb_mcu_tool/chips/bl602/device_tree/bl_factory_params_IoTKitA_40M.dts
bflb_mcu_tool/chips/bl602/device_tree/bl_factory_params_IoTKitA_None.dts
bflb_mcu_tool/chips/bl602/device_tree/bl_factory_params_IoTKitA_RC32M.dts
bflb_mcu_tool/chips/bl602/eflash_loader/eflash_loader.elf
bflb_mcu_tool/chips/bl602/eflash_loader/eflash_loader.map
bflb_mcu_tool/chips/bl602/eflash_loader/eflash_loader_24m.bin
bflb_mcu_tool/chips/bl602/eflash_loader/eflash_loader_26m.bin
bflb_mcu_tool/chips/bl602/eflash_loader/eflash_loader_32m.bin
bflb_mcu_tool/chips/bl602/eflash_loader/eflash_loader_38p4m.bin
bflb_mcu_tool/chips/bl602/eflash_loader/eflash_loader_40m.bin
bflb_mcu_tool/chips/bl602/eflash_loader/eflash_loader_cfg.conf
bflb_mcu_tool/chips/bl602/eflash_loader/eflash_loader_none.bin
bflb_mcu_tool/chips/bl602/eflash_loader/eflash_loader_rc32m.bin
bflb_mcu_tool/chips/bl602/efuse_bootheader/efuse_bootheader_cfg.conf
bflb_mcu_tool/chips/bl602/img_create_iot/img_create_cfg.conf
bflb_mcu_tool/chips/bl602/img_create_iot/img_create_cfg_boot2.conf
bflb_mcu_tool/chips/bl602/img_create_iot/img_create_cfg_mfg.conf
bflb_mcu_tool/chips/bl602/img_create_mcu/img_create_cfg.conf
bflb_mcu_tool/chips/bl602/img_create_mcu/img_create_cfg_boot2.conf
bflb_mcu_tool/chips/bl602/img_create_mcu/img_create_cfg_mfg.conf
bflb_mcu_tool/chips/bl602/partition/partition_cfg_1M.toml
bflb_mcu_tool/chips/bl602/partition/partition_cfg_1M_ota.toml
bflb_mcu_tool/chips/bl602/partition/partition_cfg_2M.toml
bflb_mcu_tool/chips/bl602/partition/partition_cfg_4M.toml
bflb_mcu_tool_uart.egg-info/PKG-INFO
bflb_mcu_tool_uart.egg-info/SOURCES.txt
bflb_mcu_tool_uart.egg-info/dependency_links.txt
bflb_mcu_tool_uart.egg-info/entry_points.txt
bflb_mcu_tool_uart.egg-info/not-zip-safe
bflb_mcu_tool_uart.egg-info/requires.txt
bflb_mcu_tool_uart.egg-info/top_level.txt